holcstore/__init__.py
holcstore/asgi.py
holcstore/settings.py
holcstore/urls.py
holcstore/wsgi.py
holcstore-0.5.9.dist-info/licenses/LICENSE
hostore/__init__.py
hostore/admin_actions.py
hostore/apps.py
hostore/views.py
hostore/migrations/0001_initial.py
hostore/migrations/0002_rename_store_testd_prm_91e86e_idx_hostore_tes_prm_897468_idx.py
hostore/migrations/0003_alter_testdatastore_unique_together_and_more.py
hostore/migrations/0004_testdatastore_created_at.py
hostore/migrations/0005_alter_testdatastore_prm.py
hostore/migrations/0006_testdatastorewithattribute.py
hostore/migrations/0007_testtimeseriesstorewithattribute.py
hostore/migrations/0008_remove_testtimeseriesstorewithattribute_hostore_tes_version_822f4b_idx_and_more.py
hostore/migrations/0009_delete_testdatastore_and_more.py
hostore/migrations/__init__.py
hostore/models/__init__.py
hostore/models/chunk_timeserie_store.py
hostore/models/hostore.py
hostore/models/manager.py
hostore/models/timeserie_store.py
hostore/tests/__init__.py
hostore/tests/test_chunk_timeserie_store.py
hostore/tests/test_chunk_timeserie_store_perf.py
hostore/tests/test_chunk_timeserie_sync.py
hostore/tests/test_import_chunks.py
hostore/tests/tests_admin_download.py
hostore/tests/tests_basics.py
hostore/tests/tests_find_groups.py
hostore/tests/tests_slice_with_delay.py
hostore/tests/tests_timeseries_store.py
hostore/tests/tests_with_attributes.py
hostore/utils/__init__.py
hostore/utils/timeseries.py
hostore/utils/ts_sync.py
hostore/utils/utils.py
hostore/utils/utils_test.py
hostore/utils/range/__init__.py
hostore/utils/range/range.py
hostore/utils/range/tests.py
holcstore-0.5.9.dist-info/METADATA
holcstore-0.5.9.dist-info/WHEEL
holcstore-0.5.9.dist-info/top_level.txt
holcstore-0.5.9.dist-info/RECORD
