Metadata-Version: 2.4
Name: holcstore
Version: 0.5.9
Summary: A Django App to efficiently store dense timeseries
Home-page: 
Author: Jean-Pierre Lartigue, Yohan Roy
Author-email: 
License: BSD-3-Clause
Classifier: Environment :: Web Environment
Classifier: Framework :: Django
Classifier: Framework :: Django :: 4.2
Classifier: Intended Audience :: Developers
Classifier: License :: OSI Approved :: BSD License
Classifier: Operating System :: OS Independent
Classifier: Programming Language :: Python
Classifier: Programming Language :: Python :: 3
Classifier: Programming Language :: Python :: 3 :: Only
Classifier: Programming Language :: Python :: 3.10
Classifier: Programming Language :: Python :: 3.11
Classifier: Programming Language :: Python :: 3.12
Classifier: Topic :: Internet :: WWW/HTTP
Classifier: Topic :: Internet :: WWW/HTTP :: Dynamic Content
Requires-Python: <=3.12,>=3.10
License-File: LICENSE
Requires-Dist: backoff>=2.2.1
Requires-Dist: Django>=4.0.0
Requires-Dist: djangorestframework>=3.14.0
Requires-Dist: lz4>=4.4.4
Requires-Dist: pandas>=1.5.0
Requires-Dist: pyarrow>=14.0.0
Requires-Dist: packaging>=22.0
Requires-Dist: requests>=2.31.0
Dynamic: license-file
